Workbook

Sheet Hashtag
A1: 只计算，IG，TT，YT
A2: 品牌 | B2: 私域发帖总数 | C2: 官号发帖 | D2: SNS总和 | E2: 红人每月发帖 | F2: 红人和SNS增量总计 | G2: 今年每月增加 | H2: 社媒总量实际统计 | I2: 目前hashtag数据 | J2: 2024年总值 | K2: 系数 | L2: 2025年目标（2024*1.5） | M2: 平均每月增加 | N2: instagram | O2: tiktok | P2: youtube | Q2: 备注：预算需求
A3: Coofandy | B3: 16 | C3: 100 | D3: =SUM(B3:C3) -> 116 | E3: 417 | F3: =D3+E3 -> 533 | G3: 600 | I3: =SUM(N3:P3) -> 17818 | J3: =I3+2*G3 -> 19018 | K3: 1.4 | L3: =J3*K3 -> 26625.2 | M3: =(L3-J3)/12 -> 633.93333 | N3: 12000 | O3: 4960 | P3: 858
A4: Ekouaer | B4: 220 | C4: 100 | D4: =SUM(B4:C4) -> 320 | E4: 594 | F4: =D4+E4 -> 914 | G4: 700 | I4: =SUM(N4:P4) -> 18836 | J4: =I4+2*G4 -> 20236 | K4: 1.5 | L4: =J4*K4 -> 30354 | M4: =(L4-J4)/12 -> 843.16667 | N4: 10900 | O4: 6836 | P4: 1100
A5: Avidlove | B5: 21 | C5: 100 | D5: =SUM(B5:C5) -> 121 | E5: 168 | F5: =D5+E5 -> 289 | G5: 300 | H5: 921 | I5: 12530 | J5: =I5+2*G5 -> 13130 | K5: 1.4 | L5: =J5*K5 -> 18382 | M5: =(L5-J5)/12 -> 437.66667 | N5: 9400 | O5: 2193 | P5: 937
A6: Zeagoo | B6: 12 | C6: 100 | D6: =SUM(B6:C6) -> 112 | E6: 306 | F6: =D6+E6 -> 418 | G6: 300 | I6: =SUM(N6:P6) -> 12591 | J6: =I6+2*G6 -> 13191 | K6: 1.4 | L6: =J6*K6 -> 18467.4 | M6: =(L6-J6)/12 -> 439.7 | N6: 7500 | O6: 4270 | P6: 821
A7: Arshiner | B7: 32 | C7: 100 | D7: =SUM(B7:C7) -> 132 | E7: 100 | F7: =D7+E7 -> 232 | G7: 200 | I7: =SUM(N7:P7) -> 1613 | J7: =I7+2*G7 -> 2013 | K7: 3.5 | L7: =J7*K7 -> 7045.5 | M7: 200 | N7: 1000 | O7: 278 | P7: 335 | Q7: 竞品需求
A8: Pinspark | B8: 18 | C8: 100 | D8: =SUM(B8:C8) -> 118 | E8: 93 | F8: =D8+E8 -> 211 | G8: 100 | H8: 447 | I8: 2020 | J8: =I8+2*G8 -> 2220 | K8: 4 | L8: =J8*K8 -> 8880 | M8: =(L8-J8)/12 -> 555 | N8: 938 | O8: 844 | P8: 238 | Q8: 竞品需求
A9: 合计 | B9: =B3+B4+B5+B6+B7+B8 -> 319 | C9: =C3+C4+C5+C6+C7+C8 -> 600 | D9: =D3+D4+D5+D6+D7+D8 -> 919 | E9: =E3+E4+E5+E6+E7+E8 -> 1678 | F9: =D9+E9 -> 2597 | G9: =SUM(G3:G8) -> 2200 | M9: =SUM(M3:M8) -> 3109.4667
A12: 品牌 | B12: 目前hashtag数据 | C12: 今年每月增加 | D12: 11月 | E12: 12月 | F12: 25年平均每月增加 | G12: 1月 | H12: 2月 | I12: 3月 | J12: 4月 | K12: 5月 | L12: 6月 | M12: 7月 | N12: 8月 | O12: 9月 | P12: 10月 | Q12: 11月 | R12: 12月
A13: Coofandy | B13: 17818 | C13: 600 | D13: =B13+C13 -> 18418 | E13: =D13+C13 -> 19018 | F13: 633.93333 | G13: =E13+F13 -> 19651.933 | H13: =G13+F13 -> 20285.867 | I13: =H13+F13 -> 20919.8 | J13: =I13+F13 -> 21553.733 | K13: =J13+F13 -> 22187.667 | L13: =K13+F13 -> 22821.6 | M13: =L13+F13 -> 23455.533 | N13: =M13+F13 -> 24089.467 | O13: =N13+F13 -> 24723.4 | P13: =O13+F13 -> 25357.333 | Q13: =P13+F13 -> 25991.267 | R13: =Q13+F13 -> 26625.2
A14: Ekouaer | B14: 18836 | C14: 700 | D14: =B14+C14 -> 19536 | E14: =D14+C14 -> 20236 | F14: 843.16667 | G14: =E14+F14 -> 21079.167 | H14: =G14+F14 -> 21922.333 | I14: =H14+F14 -> 22765.5 | J14: =I14+F14 -> 23608.667 | K14: =J14+F14 -> 24451.833 | L14: =K14+F14 -> 25295 | M14: =L14+F14 -> 26138.167 | N14: =M14+F14 -> 26981.333 | O14: =N14+F14 -> 27824.5 | P14: =O14+F14 -> 28667.667 | Q14: =P14+F14 -> 29510.833 | R14: =Q14+F14 -> 30354
A15: Avidlove | B15: 12530 | C15: 300 | D15: =B15+C15 -> 12830 | E15: =D15+C15 -> 13130 | F15: 437.66667 | G15: =E15+F15 -> 13567.667 | H15: =G15+F15 -> 14005.333 | I15: =H15+F15 -> 14443 | J15: =I15+F15 -> 14880.667 | K15: =J15+F15 -> 15318.333 | L15: =K15+F15 -> 15756 | M15: =L15+F15 -> 16193.667 | N15: =M15+F15 -> 16631.333 | O15: =N15+F15 -> 17069 | P15: =O15+F15 -> 17506.667 | Q15: =P15+F15 -> 17944.333 | R15: =Q15+F15 -> 18382
A16: Zeagoo | B16: 12591 | C16: 300 | D16: =B16+C16 -> 12891 | E16: =D16+C16 -> 13191 | F16: 439.7 | G16: =E16+F16 -> 13630.7 | H16: =G16+F16 -> 14070.4 | I16: =H16+F16 -> 14510.1 | J16: =I16+F16 -> 14949.8 | K16: =J16+F16 -> 15389.5 | L16: =K16+F16 -> 15829.2 | M16: =L16+F16 -> 16268.9 | N16: =M16+F16 -> 16708.6 | O16: =N16+F16 -> 17148.3 | P16: =O16+F16 -> 17588 | Q16: =P16+F16 -> 18027.7 | R16: =Q16+F16 -> 18467.4
A17: Arshiner | B17: 1613 | C17: 200 | D17: =B17+C17 -> 1813 | E17: =D17+C17 -> 2013 | F17: 200 | G17: =E17+F17 -> 2213 | H17: =G17+F17 -> 2413 | I17: =H17+F17 -> 2613 | J17: =I17+F17 -> 2813 | K17: =J17+F17 -> 3013 | L17: =K17+F17 -> 3213 | M17: =L17+F17 -> 3413 | N17: =M17+F17 -> 3613 | O17: =N17+F17 -> 3813 | P17: =O17+F17 -> 4013 | Q17: =P17+F17 -> 4213 | R17: =Q17+F17 -> 4413
A18: Pinspark | B18: 2020 | C18: 100 | D18: =B18+C18 -> 2120 | E18: =D18+C18 -> 2220 | F18: 555 | G18: =E18+F18 -> 2775 | H18: =G18+F18 -> 3330 | I18: =H18+F18 -> 3885 | J18: =I18+F18 -> 4440 | K18: =J18+F18 -> 4995 | L18: =K18+F18 -> 5550 | M18: =L18+F18 -> 6105 | N18: =M18+F18 -> 6660 | O18: =N18+F18 -> 7215 | P18: =O18+F18 -> 7770 | Q18: =P18+F18 -> 8325 | R18: =Q18+F18 -> 8880
C20: 社媒每月新增 | D20: 12个月新增 | E20: 25年同比增长帖子数 | F20: 25年同比年度增长帖子数 | G20: 帖子单价USD | H20: 帖子总价人民币
B21: Coofandy | C21: =B3*1.4+C3 -> 122.4 | D21: =C21*12 -> 1468.8 | E21: =C21-B3-C3 -> 6.4 | F21: =E21*12 -> 76.8 | G21: 50 | H21: =F21*G21*7 -> 26880
B22: Ekouaer | C22: =B4*1.4+C4 -> 408 | D22: =C22*12 -> 4896 | E22: =C22-B4-C4 -> 88 | F22: =E22*12 -> 1056 | G22: 40 | H22: =F22*G22*7 -> 295680
B23: Avidlove | C23: =B5*1.4+C5 -> 129.4 | D23: =C23*12 -> 1552.8 | E23: =C23-B5-C5 -> 8.4 | F23: =E23*12 -> 100.8 | G23: 40 | H23: =F23*G23*7 -> 28224
B24: Zeagoo | C24: =B6*1.4+C6 -> 116.8 | D24: =C24*12 -> 1401.6 | E24: =C24-B6-C6 -> 4.8 | F24: =E24*12 -> 57.6 | G24: 40 | H24: =F24*G24*7 -> 16128
B25: Arshiner | C25: =B7*1.4+C7 -> 144.8 | D25: =C25*12 -> 1737.6 | E25: =C25-B7-C7 -> 12.8 | F25: =E25*12 -> 153.6 | G25: 30 | H25: =F25*G25*7 -> 32256
B26: Pinspark | C26: =B8*1.4+C8 -> 125.2 | D26: =C26*12 -> 1502.4 | E26: =C26-B8-C8 -> 7.2 | F26: =E26*12 -> 86.4 | G26: 40 | H26: =F26*G26*7 -> 24192
C27: =SUM(C21:C26) -> 1046.6 | D27: =SUM(D21:D26) -> 12559.2 | E27: =SUM(E21:E26) -> 127.6 | F27: =SUM(F21:F26) -> 1531.2

Sheet 人力预算
A1: 人数 | B1: 结构 | C1: 年度人力 | D1: 品牌 | E1: 人力预算占比 | F1: 年度固有成本 | L1: 固定成本合计
A2: 9 | B2: 经理-组长-运营 | C2: =210000*SUM(A2:A9) -> 4830000 | F2: 人数 | G2: 品牌人力成本 | H2: 设计成本 | I2: 短视频+带货视频拍摄 | J2: 代理运营费 | K2: 支持部门结算
A3: 3 | B3: KOC | D3: coofandy | E3: 0.25247199 | F3: =SUM(A2:A9)*E3 -> 5.8068558 | G3: =C2*E3 -> 1219439.7 | H3: =7000*12 -> 84000 | I3: =(20000+10000)*12 -> 360000 | J3: =1000*12 -> 12000 | K3: =4000*12 -> 48000 | L3: =SUM(G3:K3) -> 1723439.7
A4: 3 | B4: tiktok运营 | D4: ekouaer | E4: 0.21779039 | F4: =SUM(A2:A9)*E4 -> 5.0091791 | G4: =C2*E4 -> 1051927.6 | H4: =7000*12 -> 84000 | I4: =(20000+10000)*12 -> 360000 | J4: =1000*12 -> 12000 | K4: =4000*12 -> 48000 | L4: =SUM(G4:K4) -> 1555927.6
A5: 2 | B5: 私域 | D5: avidlove | E5: 0.1824009 | F5: =SUM(A2:A9)*E5 -> 4.1952208 | G5: =C2*E5 -> 880996.36 | H5: =7000*12 -> 84000 | I5: =(20000+10000)*12 -> 360000 | J5: =1000*12 -> 12000 | K5: =4000*12 -> 48000 | L5: =SUM(G5:K5) -> 1384996.4
A6: 2 | B6: 编导 | D6: zeagoo | E6: 0.14549556 | F6: =SUM(A2:A9)*E6 -> 3.3463978 | G6: =C2*E6 -> 702743.55 | H6: =7000*12 -> 84000 | I6: =(10000+10000)*12 -> 240000 | J6: =1000*12 -> 12000 | K6: =4000*12 -> 48000 | L6: =SUM(G6:K6) -> 1086743.5
A7: 2 | B7: 剪辑 | D7: arshiner | E7: 0.12516217 | F7: =SUM(A2:A9)*E7 -> 2.8787299 | G7: =C2*E7 -> 604533.28 | H7: =7000*12 -> 84000 | I7: =(5000+0)*12 -> 60000 | J7: =1000*12 -> 12000 | K7: =4000*12 -> 48000 | L7: =SUM(G7:K7) -> 808533.28
A8: 1 | B8: pinterest | D8: pinspark | E8: 0.076678984 | F8: =SUM(A2:A9)*E8 -> 1.7636166 | G8: =C2*E8 -> 370359.5 | H8: =6000*12 -> 72000 | I8: =(5000+5000)*12 -> 120000 | J8: =800*12 -> 9600 | K8: =3000*12 -> 36000 | L8: =SUM(G8:K8) -> 607959.5
A9: 1 | B9: 亚马逊post
E10: 备注：人力摊算按照实际业务工资发放在整体工资中占比

Sheet 预算规划
A1: 品牌 | B1: 24年预算 | C1: 24年实际推广预算 | D1: 2015年预算同比 | E1: 25年渠道预算 | F1: 25年预算占比 | G1: 25年预算 | H1: 人力总消耗预算 | I1: 人力预算占比 | J1: 年度固有成本 | O1: 推广预算 | P1: 旗舰店铺follow花费 | Q1: 社媒剩余推广费用 | R1: 社媒hashtag额外花费 | S1: Intagram费用 | W1: 新渠道测试费用 | Y1: 目标 | AG1: 年度自然涨粉 | AO1: 年度广告涨粉 | AV1: 年度自然高级互动 | BD1: 年度广告高级互动
J2: 品牌人力成本 | K2: 设计成本 | L2: 短视频+带货视频拍摄 | M2: 代理运营费 | N2: 支持部门结算 | S2: 粉丝广告占比 | T2: 粉丝广告费用 | U2: 互动广告占比 | V2: 互动广告费用 | W2: 占比 | X2: 费用 | Y2: 24年粉丝数 | Z2: 24年高级互动数量 | AA2: 每月新增hashtag数 | AB2: 新增粉丝量 | AC2: 活跃粉丝占比 | AD2: 年度高级互动数 | AE2: 年度粉丝增幅 | AF2: 年度互动增幅 | AG2: 年度增长系数 | AH2: 24年平均月度增长 | AI2: Instagram | AJ2: youtube | AK2: Facebook小组 | AL2: tiktok | AM2: pinterest | AN2: reddit | AO2: Instagram CPF | AP2: Instagram涨粉量 | AQ2: youtube | AR2: Facebook小组 | AS2: tiktok | AT2: pinterest | AU2: reddit | AV2: 年度增长系数 | AW2: 24年平均月度高级互动 | AX2: Instagram | AY2: youtube | AZ2: Facebook小组 | BA2: tiktok | BB2: pinterest | BC2: reddit | BD2: Instagram CPE | BE2: Instagram广告高级互动量 | BF2: youtube | BG2: Facebook小组 | BH2: tiktok | BI2: pinterest | BJ2: reddit
A3: coofandy | B3: 2124380.8 | C3: =B21 -> 1549614.4 | D3: =(Q3-C3)/C3 -> 1.2586923 | E3: 65894273 | F3: 0.08 | G3: =E3*F3 -> 5271541.8 | H3: =M11 -> 4830000 | I3: 0.25247199 | J3: =H3*I3 -> 1219439.7 | K3: =7000*12 -> 84000 | L3: =(20000+10000)*12 -> 360000 | M3: =1000*12 -> 12000 | N3: =4000*12 -> 48000 | O3: =G3-J3-K3-L3-M3-N3 -> 3548102.1 | P3: =4000*12 -> 48000 | Q3: =O3-P3 -> 3500102.1 | R3: =Hashtag!H21 -> 26880 | S3: 0.8 | T3: =(Q3-R3)*S3 -> 2778577.7 | U3: 0.1 | V3: =(Q3-R3)*S3*U3 -> 277857.77 | W3: =1-S3-U3 -> 0.1 | X3: =(Q3-R3)*W3 -> 347322.21 | Y3: 933619 | Z3: 1060000 | AA3: 122.4 | AB3: =SUM(AI3:AU3) -> 355559.51 | AC3: 0.18983515 | AD3: =SUM(AX3:BJ3) -> 4411953.3 | AE3: =AB3/Y3 -> 0.38084005 | AF3: =(AD3-Z3)/Z3 -> 3.1622201 | AG3: 2 | AH3: 2000 | AI3: =AH3*AG3*12 -> 48000 | AJ3: =100*12 -> 1200 | AK3: =30*12 -> 360 | AL3: =50*12 -> 600 | AM3: =5*12 -> 60 | AN3: 0 | AO3: 1.3 | AP3: =T3/7/AO3 -> 305338.21 | AQ3: 0 | AR3: 0 | AS3: 0 | AT3: 0 | AU3: 0 | AV3: =(1+AE3)*(1+40%) -> 1.9331761 | AW3: =158*60 -> 9480 | AX3: =AW3*AV3*12 -> 219918.11 | AY3: =1200*12 -> 14400 | AZ3: =4000*12 -> 48000 | BA3: =2800*12 -> 33600 | BB3: =100*12 -> 1200 | BC3: 0 | BD3: 0.05 | BE3: =T3/12/AX11*BA11*12*0.9+V3/7/BD3 -> 4094835.1 | BF3: 0 | BG3: 0 | BH3: 0 | BI3: 0 | BJ3: 0
A4: ekouaer | B4: 1452142.9 | C4: =B22 -> 827054.56 | D4: =(Q4-C4)/C4 -> 0.33281369 | E4: 46303954 | F4: 0.06 | G4: =E4*F4 -> 2778237.2 | I4: 0.21779039 | J4: =H3*I4 -> 1051927.6 | K4: =7000*12 -> 84000 | L4: =(20000+10000)*12 -> 360000 | M4: =1000*12 -> 12000 | N4: =4000*12 -> 48000 | O4: =G4-J4-K4-L4-M4-N4 -> 1222309.6 | P4: =10000*12 -> 120000 | Q4: =O4-P4 -> 1102309.6 | R4: =Hashtag!H22 -> 295680 | S4: 0.9 | T4: =(Q4-R4)*S4 -> 725966.67 | U4: 0.1 | V4: =(Q4-R4)*S4*U4 -> 72596.667 | W4: =1-S4-U4 -> 0 | X4: =(Q4-R4)*W4 -> 0 | Y4: 1362941 | Z4: 1120000 | AA4: 408 | AB4: =SUM(AI4:AU4) -> 128737.86 | AC4: 0.5483135 | AD4: =SUM(AX4:BJ4) -> 1810469.9 | AE4: =AB4/Y4 -> 0.094455928 | AF4: =(AD4-Z4)/Z4 -> 0.61649095 | AG4: 2.1 | AH4: 1500 | AI4: =AH4*AG4*12 -> 37800 | AJ4: =200*12 -> 2400 | AK4: =120*12 -> 1440 | AL4: =600*12 -> 7200 | AM4: =10*12 -> 120 | AN4: 0 | AO4: 1.3 | AP4: =T4/7/AO4 -> 79776.558 | AQ4: 0 | AR4: 0 | AS4: 0 | AT4: 0 | AU4: 0 | AV4: =(1+AE4)*(1+40%) -> 1.5322383 | AW4: =139*60 -> 8340 | AX4: =AW4*AV4*12 -> 153346.41 | AY4: =1500*12 -> 18000 | AZ4: =6000*12 -> 72000 | BA4: =5000*12 -> 60000 | BB4: =50*12 -> 600 | BC4: 0 | BD4: 0.05 | BE4: =T4/12/AX12*BA12*12*0.9+V4/7/BD4 -> 1506523.4 | BF4: 0 | BG4: 0 | BH4: 0 | BI4: 0 | BJ4: 0
A5: avidlove | B5: 1340487.6 | C5: =B23 -> 789410.8 | D5: =(Q5-C5)/C5 -> 0.15642912 | E5: 23458940 | F5: 0.1 | G5: =E5*F5 -> 2345894 | I5: 0.1824009 | J5: =H3*I5 -> 880996.36 | K5: =7000*12 -> 84000 | L5: =(20000+10000)*12 -> 360000 | M5: =1000*12 -> 12000 | N5: =4000*12 -> 48000 | O5: =G5-J5-K5-L5-M5-N5 -> 960897.64 | P5: =4000*12 -> 48000 | Q5: =O5-P5 -> 912897.64 | R5: =Hashtag!H23 -> 28224 | S5: 0.8 | T5: =(Q5-R5)*S5 -> 707738.91 | U5: 0.1 | V5: =(Q5-R5)*S5*U5 -> 70773.891 | W5: =1-S5-U5 -> 0.1 | X5: =(Q5-R5)*W5 -> 88467.364 | Y5: 683930.4 | Z5: 1000000 | AA5: 129.4 | AB5: =SUM(AI5:AU5) -> 96852.574 | AC5: 0.30977451 | AD5: =SUM(AX5:BJ5) -> 1530705.2 | AE5: =AB5/Y5 -> 0.14161174 | AF5: =(AD5-Z5)/Z5 -> 0.53070517 | AG5: 2 | AH5: 1000 | AI5: =AH5*AG5*12 -> 24000 | AJ5: =600*12 -> 7200 | AK5: =100*12 -> 1200 | AL5: =100*12 -> 1200 | AM5: =5*12 -> 60 | AN5: 0 | AO5: 1.6 | AP5: =T5/7/AO5 -> 63190.974 | AQ5: 0 | AR5: 0 | AS5: 0 | AT5: 0 | AU5: 0 | AV5: =(1+AE5)*(1+40%) -> 1.5982564 | AW5: =353*60 -> 21180 | AX5: =AW5*AV5*12 -> 406212.86 | AY5: =2000*12 -> 24000 | AZ5: =14000*12 -> 168000 | BA5: =1000*12 -> 12000 | BB5: =200*12 -> 2400 | BC5: 0 | BD5: 0.05 | BE5: =T5/12/AX13*BA13*12*0.9+V5/7/BD5 -> 918092.27 | BF5: 0 | BG5: 0 | BH5: 0 | BI5: 0 | BJ5: 0
A6: zeagoo | B6: 996846.68 | C6: =B24 -> 288287.39 | D6: =(Q6-C6)/C6 -> 0.44939968 | E6: 15525872 | F6: 0.1 | G6: =E6*F6 -> 1552587.2 | I6: 0.14549556 | J6: =H3*I6 -> 702743.55 | K6: =7000*12 -> 84000 | L6: =(10000+10000)*12 -> 240000 | M6: =1000*12 -> 12000 | N6: =4000*12 -> 48000 | O6: =G6-J6-K6-L6-M6-N6 -> 465843.65 | P6: =4000*12 -> 48000 | Q6: =O6-P6 -> 417843.65 | R6: =Hashtag!H24 -> 16128 | S6: 0.85 | T6: =(Q6-R6)*S6 -> 341458.31 | U6: 0.1 | V6: =(Q6-R6)*S6*U6 -> 34145.831 | W6: =1-S6-U6 -> 0.05 | X6: =(Q6-R6)*W6 -> 20085.783 | Y6: 848645.1 | Z6: 310000 | AA6: 116.8 | AB6: =SUM(AI6:AU6) -> 51264.191 | AC6: 0.11783426 | AD6: =SUM(AX6:BJ6) -> 621522.25 | AE6: =AB6/Y6 -> 0.060407102 | AF6: =(AD6-Z6)/Z6 -> 1.0049105 | AG6: 1.3 | AH6: 800 | AI6: =AH6*AG6*12 -> 12480 | AJ6: =50*12 -> 600 | AK6: =50*12 -> 600 | AL6: 0 | AM6: =5*12 -> 60 | AN6: 0 | AO6: 1.3 | AP6: =T6/7/AO6 -> 37522.891 | AQ6: 0 | AR6: 0 | AS6: 0 | AT6: 0 | AU6: 0 | AV6: =(1+AE6)*(1+40%) -> 1.4845699 | AW6: =58*60 -> 3480 | AX6: =AW6*AV6*12 -> 61995.641 | AY6: =500*12 -> 6000 | AZ6: =1200*12 -> 14400 | BA6: =500*12 -> 6000 | BB6: =20*12 -> 240 | BC6: 0 | BD6: 0.05 | BE6: =T6/12/AX14*BA14*12*0.9+V6/7/BD6 -> 532886.56 | BF6: 0 | BG6: 0 | BH6: 0 | BI6: 0 | BJ6: 0
A7: arshiner | B7: 716190.43 | C7: =B25 -> 666188.14 | D7: =(Q7-C7)/C7 -> 0.025636279 | E7: 6890000 | F7: 0.22 | G7: =E7*F7 -> 1515800 | I7: 0.12516217 | J7: =H3*I7 -> 604533.28 | K7: =7000*12 -> 84000 | L7: =(5000+0)*12 -> 60000 | M7: =1000*12 -> 12000 | N7: =4000*12 -> 48000 | O7: =G7-J7-K7-L7-M7-N7 -> 707266.72 | P7: =2000*12 -> 24000 | Q7: =O7-P7 -> 683266.72 | R7: =Hashtag!H25 -> 32256 | S7: 0.9 | T7: =(Q7-R7)*S7 -> 585909.65 | U7: 0.1 | V7: =(Q7-R7)*S7*U7 -> 58590.965 | W7: =1-S7-U7 -> 0 | X7: =(Q7-R7)*W7 -> 0 | Y7: 285878.5 | Z7: 200000 | AA7: 144.8 | AB7: =SUM(AI7:AU7) -> 40090.204 | AC7: 0.44625242 | AD7: =SUM(AX7:BJ7) -> 656649.21 | AE7: =AB7/Y7 -> 0.14023511 | AF7: =(AD7-Z7)/Z7 -> 2.283246 | AG7: 1.2 | AH7: 200 | AI7: =AH7*AG7*12 -> 2880 | AJ7: =5*12 -> 60 | AK7: =20*12 -> 240 | AL7: =40*12 -> 480 | AM7: =3*12 -> 36 | AN7: 0 | AO7: 2.3 | AP7: =T7/7/AO7 -> 36391.904 | AQ7: 0 | AR7: 0 | AS7: 0 | AT7: 0 | AU7: 0 | AV7: =(1+AE7)*(1+40%) -> 1.5963292 | AW7: =74*60 -> 4440 | AX7: =AW7*AV7*12 -> 85052.418 | AY7: =50*12 -> 600 | AZ7: =1000*12 -> 12000 | BA7: =300*12 -> 3600 | BB7: =10*12 -> 120 | BC7: 0 | BD7: 0.05 | BE7: =T7/12/AX15*BA15*12*0.9+V7/7/BD7 -> 555276.74 | BF7: 0 | BG7: 0 | BH7: 0 | BI7: 0 | BJ7: 0
A8: pinspark | B8: 429456.27 | C8: =B26 -> 149093.51 | D8: =(Q8-C8)/C8 -> 0.074227524 | E8: 2331771 | F8: 0.35 | G8: =E8*F8 -> 816119.85 | I8: 0.076678984 | J8: =H3*I8 -> 370359.5 | K8: =6000*12 -> 72000 | L8: =(5000+5000)*12 -> 120000 | M8: =800*12 -> 9600 | N8: =3000*12 -> 36000 | O8: =G8-J8-K8-L8-M8-N8 -> 208160.35 | P8: =4000*12 -> 48000 | Q8: =O8-P8 -> 160160.35 | R8: =Hashtag!H26 -> 24192 | S8: 0.8 | T8: =(Q8-R8)*S8 -> 108774.68 | U8: 0.1 | V8: =(Q8-R8)*S8*U8 -> 10877.468 | W8: =1-S8-U8 -> 0.1 | X8: =(Q8-R8)*W8 -> 13596.835 | Y8: 5688.8 | Z8: 30000 | AA8: 125.2 | AB8: =SUM(AI8:AU8) -> 18760.994 | AC8: 0.38831683 | AD8: =SUM(AX8:BJ8) -> 86584.843 | AE8: =AB8/Y8 -> 3.2978825 | AF8: =(AD8-Z8)/Z8 -> 1.8861614 | AG8: 2 | AH8: 300 | AI8: =AH8*AG8*12 -> 7200 | AJ8: =30*12 -> 360 | AK8: 0 | AL8: =70*12 -> 840 | AM8: 0 | AN8: 0 | AO8: 1.5 | AP8: =T8/7/AO8 -> 10359.494 | AQ8: 0 | AR8: 0 | AS8: 0 | AT8: 0 | AU8: 0 | AV8: =2*(1+40%) -> 2.8 | AW8: =20*60 -> 1200 | AX8: =AW8*AV8*12 -> 40320 | AY8: =500*12 -> 6000 | AZ8: =15*12 -> 180 | BA8: =200*12 -> 2400 | BB8: 0 | BC8: 0 | BD8: 0.05 | BE8: =T8/12/AX16*BA16*12*0.9+V8/7/BD8 -> 37684.793 | BF8: 0 | BG8: 0 | BH8: 0 | BI8: 0 | BJ8: 0
C9: 备注：仅社媒推广费用 | R9: 各个品牌的发帖数
B10: 2024年全年 | C10: 总曝光 | D10: IG渠道曝光 | E10: 自然占比 | F10: 自然 | G10: IG广告曝光 | H10: 其他曝光 | I10: 纯自然曝光 | J10: 自然曝光占比 | Q10: 品牌 | R10: 粉丝数 | S10: 每月净增粉丝数 | T10: 1月 | U10: 2月 | V10: 3月 | W10: 4月 | X10: 5月 | Y10: 6月 | Z10: 7月 | AA10: 8月 | AB10: 9月 | AC10: 10月 | AD10: 11月 | AE10: 12月 | AG10: 年度费用RMB | AH10: 月度费用RMB | AI10: 月度广告涨粉 | AJ10: 平均涨粉成本 | AW10: 月度实际推广 | AX10: 月度实际推广RMB | AY10: IG月度高级互动 | AZ10: IG自然高级互动 | BA10: 广告高级互动
B11: coofandy | C11: =I11+G11 -> 172010000 | D11: 103420000 | E11: 0.12 | F11: =D11*E11 -> 12410400 | G11: =D11-F11 -> 91009600 | H11: 68590000 | I11: =F11+H11 -> 81000400 | J11: =I11/C11 -> 0.47090518 | K11: 9 | L11: 经理-组长-运营 | M11: =210000*SUM(K11:K18) -> 4830000 | Q11: Coofandy | R11: 933619 | S11: =AB3/12 -> 29629.959 | T11: =R11+S11 -> 963248.96 | U11: =T11+S11 -> 992878.92 | V11: =U11+S11 -> 1022508.9 | W11: =V11+S11 -> 1052138.8 | X11: =W11+S11 -> 1081768.8 | Y11: =X11+S11 -> 1111398.8 | Z11: =Y11+S11 -> 1141028.7 | AA11: =Z11+S11 -> 1170658.7 | AB11: =AA11+S11 -> 1200288.6 | AC11: =AB11+S11 -> 1229918.6 | AD11: =AC11+S11 -> 1259548.5 | AE11: =AD11+S11 -> 1289178.5 | AG11: =Q3 -> 3500102.1 | AH11: =AG11/12 -> 291675.18 | AI11: =AH11/7/AO3 -> 32052.217 | AJ11: =AG11/(AI3+AI11*12)/7 -> 1.1557648 | AV11: Coofandy | AW11: 18590.77 | AX11: =AW11*7 -> 130135.39 | AY11: 181259 | AZ11: 9480 | BA11: =AY11-AZ11 -> 171779
B12: ekouaer | C12: =I12+G12 -> 98430000 | D12: 51710000 | E12: 0.12 | F12: =D12*E12 -> 6205200 | G12: =D12-F12 -> 45504800 | H12: 46720000 | I12: =F12+H12 -> 52925200 | J12: =I12/C12 -> 0.53769379 | K12: 3 | L12: KOC | Q12: Ekouaer | R12: 1354028 | S12: =AB4/12 -> 10728.155 | T12: =R12+S12 -> 1364756.2 | U12: =T12+S12 -> 1375484.3 | V12: =U12+S12 -> 1386212.5 | W12: =V12+S12 -> 1396940.6 | X12: =W12+S12 -> 1407668.8 | Y12: =X12+S12 -> 1418396.9 | Z12: =Y12+S12 -> 1429125.1 | AA12: =Z12+S12 -> 1439853.2 | AB12: =AA12+S12 -> 1450581.4 | AC12: =AB12+S12 -> 1461309.5 | AD12: =AC12+S12 -> 1472037.7 | AE12: =AD12+S12 -> 1482765.9 | AG12: =Q4 -> 1102309.6 | AH12: =AG12/12 -> 91859.136 | AI12: =AH12/7/AO4 -> 10094.411 | AJ12: =AG12/(AI4+AI12*12)/7 -> 0.99081297 | AV12: Ekouaer | AW12: 11617.24 | AX12: =AW12*7 -> 81320.68 | AY12: 170031 | AZ12: 8340 | BA12: =AY12-AZ12 -> 161691
B13: avidlove | C13: =I13+G13 -> 79200000 | D13: 24340000 | E13: 0.35 | F13: =D13*E13 -> 8519000 | G13: =D13-F13 -> 15821000 | H13: 54860000 | I13: =F13+H13 -> 63379000 | J13: =I13/C13 -> 0.8002399 | K13: 3 | L13: tiktok运营 | Q13: Avidlove | R13: 677770.35 | S13: =AB5/12 -> 8071.0478 | T13: =R13+S13 -> 685841.4 | U13: =T13+S13 -> 693912.45 | V13: =U13+S13 -> 701983.49 | W13: =V13+S13 -> 710054.54 | X13: =W13+S13 -> 718125.59 | Y13: =X13+S13 -> 726196.64 | Z13: =Y13+S13 -> 734267.69 | AA13: =Z13+S13 -> 742338.73 | AB13: =AA13+S13 -> 750409.78 | AC13: =AB13+S13 -> 758480.83 | AD13: =AC13+S13 -> 766551.88 | AE13: =AD13+S13 -> 774622.92 | AG13: =Q5 -> 912897.64 | AH13: =AG13/12 -> 76074.803 | AI13: =AH13/7/AO5 -> 6792.3931 | AJ13: =AG13/(AI5+AI13*12)/7 -> 1.236049 | AV13: Avidlove | AW13: 10965.32 | AX13: =AW13*7 -> 76757.24 | AY13: 107447 | AZ13: 21180 | BA13: =AY13-AZ13 -> 86267
B14: zeagoo | C14: =I14+G14 -> 28110000 | D14: 19600000 | E14: 0.06 | F14: =D14*E14 -> 1176000 | G14: =D14-F14 -> 18424000 | H14: 8510000 | I14: =F14+H14 -> 9686000 | J14: =I14/C14 -> 0.34457488 | K14: 2 | L14: 私域 | Q14: Zeagoo | R14: 837907.13 | S14: =AB6/12 -> 4272.0159 | T14: =R14+S14 -> 842179.15 | U14: =T14+S14 -> 846451.17 | V14: =U14+S14 -> 850723.18 | W14: =V14+S14 -> 854995.2 | X14: =W14+S14 -> 859267.21 | Y14: =X14+S14 -> 863539.23 | Z14: =Y14+S14 -> 867811.25 | AA14: =Z14+S14 -> 872083.26 | AB14: =AA14+S14 -> 876355.28 | AC14: =AB14+S14 -> 880627.29 | AD14: =AC14+S14 -> 884899.31 | AE14: =AD14+S14 -> 889171.33 | AG14: =Q6 -> 417843.65 | AH14: =AG14/12 -> 34820.304 | AI14: =AH14/7/AO6 -> 3826.4071 | AJ14: =AG14/(AI6+AI14*12)/7 -> 1.022177 | AV14: Zeagoo | AW14: 3237.82 | AX14: =AW14*7 -> 22664.74 | AY14: 35586 | AZ14: 3480 | BA14: =AY14-AZ14 -> 32106
B15: arshiner | C15: =I15+G15 -> 7590000 | D15: 5610000 | E15: 0.1 | F15: =D15*E15 -> 561000 | G15: =D15-F15 -> 5049000 | H15: 1980000 | I15: =F15+H15 -> 2541000 | J15: =I15/C15 -> 0.33478261 | K15: 2 | L15: 编导 | Q15: Arshiner | R15: 288124 | S15: =AB7/12 -> 3340.8503 | T15: =R15+S15 -> 291464.85 | U15: =T15+S15 -> 294805.7 | V15: =U15+S15 -> 298146.55 | W15: =V15+S15 -> 301487.4 | X15: =W15+S15 -> 304828.25 | Y15: =X15+S15 -> 308169.1 | Z15: =Y15+S15 -> 311509.95 | AA15: =Z15+S15 -> 314850.8 | AB15: =AA15+S15 -> 318191.65 | AC15: =AB15+S15 -> 321532.5 | AD15: =AC15+S15 -> 324873.35 | AE15: =AD15+S15 -> 328214.2 | AG15: =Q7 -> 683266.72 | AH15: =AG15/12 -> 56938.893 | AI15: =AH15/7/AO7 -> 3536.5772 | AJ15: =AG15/(AI7+AI15*12)/7 -> 2.1538359 | AV15: Arshiner | AW15: 4140.68 | AX15: =AW15*7 -> 28984.76 | AY15: 25760 | AZ15: 4440 | BA15: =AY15-AZ15 -> 21320
B16: pinspark | C16: =I16+G16 -> 4230000 | D16: 1870000 | E16: 0.2 | F16: =D16*E16 -> 374000 | G16: =D16-F16 -> 1496000 | H16: 2360000 | I16: =F16+H16 -> 2734000 | J16: =I16/C16 -> 0.6463357 | K16: 2 | L16: 剪辑 | Q16: Pinspark | R16: 5688.8 | S16: =AB8/12 -> 1563.4161 | T16: =R16+S16 -> 7252.2161 | U16: =T16+S16 -> 8815.6323 | V16: =U16+S16 -> 10379.048 | W16: =V16+S16 -> 11942.465 | X16: =W16+S16 -> 13505.881 | Y16: =X16+S16 -> 15069.297 | Z16: =Y16+S16 -> 16632.713 | AA16: =Z16+S16 -> 18196.129 | AB16: =AA16+S16 -> 19759.545 | AC16: =AB16+S16 -> 21322.961 | AD16: =AC16+S16 -> 22886.378 | AE16: =AD16+S16 -> 24449.794 | AG16: =Q8 -> 160160.35 | AH16: =AG16/12 -> 13346.696 | AI16: =AH16/7/AO8 -> 1271.1139 | AJ16: =AG16/(AI8+AI16*12)/7 -> 1.0190031 | AV16: Pinspark | AW16: 2000.53 | AX16: =AW16*7 -> 14003.71 | AY16: 2145 | AZ16: 1200 | BA16: =AY16-AZ16 -> 945
K17: 1 | L17: pinterest | AV17: 自然高级互动占比
K18: 1 | L18: 亚马逊post | R18: 年均高级互动系数 | S18: 1月 | T18: 2月 | U18: 3月 | V18: 4月 | W18: 5月 | X18: 6月 | Y18: 7月 | Z18: 8月 | AA18: 9月 | AB18: 10月 | AC18: 11月 | AD18: 12月 | AE18: 合计 | AF18: 24年合计 | AH18: 主动行建议 | AV18: Coofandy | AW18: =SUM(AX3:BC3)/AD3 -> 0.071877033
Q19: Coofandy | R19: 0.11 | S19: =T11*R19 -> 105957.39 | T19: =U11*R19 -> 109216.68 | U19: =V11*R19 -> 112475.98 | V19: =W11*R19 -> 115735.27 | W19: =X11*R19 -> 118994.57 | X19: =Y11*R19 -> 122253.86 | Y19: =Z11*R19 -> 125513.16 | Z19: =AA11*R19 -> 128772.45 | AA19: =AB11*R19 -> 132031.75 | AB19: =AC11*R19 -> 135291.04 | AC19: =AD11*R19 -> 138550.34 | AD19: =AE11*R19 -> 141809.64 | AE19: =SUM(S19:AD19) -> 1486602.1 | AF19: 1060000 | AV19: Ekouaer | AW19: =SUM(AX4:BC4)/AD4 -> 0.16788261
B20: 24年推广预算合计 | E20: 1月 | F20: 2月 | G20: 3月 | H20: 4月 | I20: 5月 | J20: 6月 | K20: 7月 | L20: 8月 | M20: 9月 | N20: 10月 | O20: 11月 | P20: 12月 | Q20: Ekouaer | R20: 0.06 | S20: =T12*R20 -> 81885.369 | T20: =U12*R20 -> 82529.059 | U20: =V12*R20 -> 83172.748 | V20: =W12*R20 -> 83816.437 | W20: =X12*R20 -> 84460.126 | X20: =Y12*R20 -> 85103.816 | Y20: =Z12*R20 -> 85747.505 | Z20: =AA12*R20 -> 86391.194 | AA20: =AB12*R20 -> 87034.884 | AB20: =AC12*R20 -> 87678.573 | AC20: =AD12*R20 -> 88322.262 | AD20: =AE12*R20 -> 88965.951 | AE20: =SUM(S20:AD20) -> 1025107.9 | AF20: 1120000 | AV20: Avidlove | AW20: =SUM(AX5:BC5)/AD5 -> 0.4002161
B21: =SUM(E21:P21) -> 1549614.4 | C21: Coofandy | E21: 113924.91 | F21: 96439.674 | G21: 111675.44 | H21: 77754.513 | I21: 99478.749 | J21: 117114.6 | K21: 108776.19 | L21: 137349.81 | M21: 257564.23 | N21: 143178.76 | O21: 143178.76 | P21: 143178.76 | Q21: Avidlove | R21: 0.12 | S21: =T13*R21 -> 82300.968 | T21: =U13*R21 -> 83269.493 | U21: =V13*R21 -> 84238.019 | V21: =W13*R21 -> 85206.545 | W21: =X13*R21 -> 86175.071 | X21: =Y13*R21 -> 87143.596 | Y21: =Z13*R21 -> 88112.122 | Z21: =AA13*R21 -> 89080.648 | AA21: =AB13*R21 -> 90049.174 | AB21: =AC13*R21 -> 91017.699 | AC21: =AD13*R21 -> 91986.225 | AD21: =AE13*R21 -> 92954.751 | AE21: =SUM(S21:AD21) -> 1051534.3 | AF21: 1000000 | AV21: Zeagoo | AW21: =SUM(AX6:BC6)/AD6 -> 0.14261057
B22: =SUM(E22:P22) -> 827054.56 | C22: Ekouaer | E22: 7916.9089 | F22: 42102.804 | G22: 39392.666 | H22: 43714.991 | I22: 49049.66 | J22: 60414.614 | K22: 82392.279 | L22: 85719.329 | M22: 259567.7 | N22: 52261.202 | O22: 52261.202 | P22: 52261.202 | Q22: Zeagoo | R22: 0.03 | S22: =T14*R22 -> 25265.375 | T22: =U14*R22 -> 25393.535 | U22: =V14*R22 -> 25521.695 | V22: =W14*R22 -> 25649.856 | W22: =X14*R22 -> 25778.016 | X22: =Y14*R22 -> 25906.177 | Y22: =Z14*R22 -> 26034.337 | Z22: =AA14*R22 -> 26162.498 | AA22: =AB14*R22 -> 26290.658 | AB22: =AC14*R22 -> 26418.819 | AC22: =AD14*R22 -> 26546.979 | AD22: =AE14*R22 -> 26675.14 | AE22: =SUM(S22:AD22) -> 311643.09 | AF22: 310000 | AV22: Arshiner | AW22: =SUM(AX7:BC7)/AD7 -> 0.15437834
B23: =SUM(E23:P23) -> 789410.8 | C23: Avidlove | E23: 22561.395 | F23: 30590.907 | G23: 16294.224 | H23: 23396.277 | I23: 39699.873 | J23: 50462.526 | K23: 50353.018 | L23: 79266.758 | M23: 102560.77 | N23: 124741.68 | O23: 124741.68 | P23: 124741.68 | Q23: Arshiner | R23: 0.05 | S23: =T15*R23 -> 14573.243 | T23: =U15*R23 -> 14740.285 | U23: =V15*R23 -> 14907.328 | V23: =W15*R23 -> 15074.37 | W23: =X15*R23 -> 15241.413 | X23: =Y15*R23 -> 15408.455 | Y23: =Z15*R23 -> 15575.498 | Z23: =AA15*R23 -> 15742.54 | AA23: =AB15*R23 -> 15909.583 | AB23: =AC15*R23 -> 16076.625 | AC23: =AD15*R23 -> 16243.668 | AD23: =AE15*R23 -> 16410.71 | AE23: =SUM(S23:AD23) -> 185903.72 | AF23: 200000 | AV23: Pinspark | AW23: =SUM(AX8:BC8)/AD8 -> 0.56476398
B24: =SUM(E24:P24) -> 288287.39 | C24: Zeagoo | E24: 20351.025 | F24: 20982.48 | G24: 25664.002 | H24: 22003.137 | I24: 28813.241 | J24: 31106.489 | K24: 34070.102 | L24: 26041.429 | M24: 57265.487 | N24: 7330 | O24: 7330 | P24: 7330 | Q24: Pinspark | R24: 0.6 | S24: =T16*R24 -> 4351.3297 | T24: =U16*R24 -> 5289.3794 | U24: =V16*R24 -> 6227.4291 | V24: =W16*R24 -> 7165.4787 | W24: =X16*R24 -> 8103.5284 | X24: =Y16*R24 -> 9041.5781 | Y24: =Z16*R24 -> 9979.6278 | Z24: =AA16*R24 -> 10917.677 | AA24: =AB16*R24 -> 11855.727 | AB24: =AC16*R24 -> 12793.777 | AC24: =AD16*R24 -> 13731.827 | AD24: =AE16*R24 -> 14669.876 | AE24: =SUM(S24:AD24) -> 114127.24 | AF24: 30000
B25: =SUM(E25:P25) -> 666188.14 | C25: Arshiner | E25: 11580.886 | F25: 5072.7481 | G25: 6688.8319 | H25: 7136.6226 | I25: 8329.5337 | J25: 19141.091 | K25: 30306.829 | L25: 31201.701 | M25: 33897.417 | N25: 170944.16 | O25: 170944.16 | P25: 170944.16
B26: =SUM(E26:P26) -> 149093.51 | C26: Pinspark | E26: 1161.6524 | F26: 762.08048 | G26: 780.661 | H26: 1145.262 | I26: 1061.634 | J26: 2008.107 | K26: 17993.613 | L26: 13803.657 | M26: 11176.827 | N26: 33066.673 | O26: 33066.673 | P26: 33066.673

Sheet Campaign
A1: 品牌 | B1: 季度 | C1: campaign预算 | D1: Q1 | G1: Q2 | I1: Q3 | L1: Q4
B2: 活动名称 | D2: New Year | E2: Valentine's Day | F2: NYFW SS FASHION TREND | G2: Wedding season+Graduation season Anniversary | H2: Father's Day | I2: Prime Day+Independence Day(7.1-7.4) | J2: Oktoberfest-DE | K2: New York Fashion Week+Fall prime day | L2: Halloween+Black Friday & Cyber Monday+Christmas
B3: 时间段 | D3: 1.1-2.9 | E3: 2.1-2.14 | F3: 2.15-3.31 | G3: 4.15-6.15 | H3: 6.1-6.30 | I3: 7.1-7.30 | J3: Sept/Oct | K3: 2025.9.1-10.21 | L3: 10.22-10.31
B4: 天数 | D4: 39 | E4: 13 | F4: 44 | G4: 61 | H4: 30 | I4: 30 | K4: 50 | L4: 9
B5: 级别 | D5: A+ | E5: C | F5: C | G5: A+ | H5: B | I5: A+ | J5: C | K5: S | L5: A+ | M5: campaign预算占比
A6: coofandy | B6: 预算 | C6: =SUM(D6:L6) -> 777000 | D6: =20000*7 -> 140000 | E6: =2000*7 -> 14000 | F6: =2000*7 -> 14000 | G6: =20000*7 -> 140000 | H6: =5000*7 -> 35000 | I6: =20000*7 -> 140000 | J6: =2000*7 -> 14000 | K6: =30000*7 -> 210000 | L6: =10000*7 -> 70000 | M6: =C6/(预算规划!G3+C6) -> 0.12846071 | N6: CPM=3，CPF=1，CPE=0.05
A7: ekouaer
A8: avidlove
A9: zeagoo
A10: arshiner
A11: pinspark
F15: 45952 | G15: 45961 | H15: =DATEDIF(F15,G15,"D") -> 9
